README.txt
setup.py
docs/HISTORY.txt
src/PyWhatCounts/LICENSE.GPL
src/PyWhatCounts/LICENSE.txt
src/PyWhatCounts/README.txt
src/PyWhatCounts/Wrapper.py
src/PyWhatCounts/__init__.py
src/PyWhatCounts/config.py
src/PyWhatCounts/exceptions.py
src/PyWhatCounts/version.txt
src/PyWhatCounts.egg-info/PKG-INFO
src/PyWhatCounts.egg-info/SOURCES.txt
src/PyWhatCounts.egg-info/dependency_links.txt
src/PyWhatCounts.egg-info/entry_points.txt
src/PyWhatCounts.egg-info/namespace_packages.txt
src/PyWhatCounts.egg-info/not-zip-safe
src/PyWhatCounts.egg-info/requires.txt
src/PyWhatCounts.egg-info/top_level.txt
src/PyWhatCounts/tests/README.txt
src/PyWhatCounts/tests/__init__.py
src/PyWhatCounts/tests/config.py
src/PyWhatCounts/tests/runalltests.py
src/PyWhatCounts/tests/testActions.py
src/PyWhatCounts/tests/testHelperMethods.py
src/PyWhatCounts/tests/testQueries.py