Metadata-Version: 1.0
Name: PyWhatCounts
Version: 0.2
Summary: Python wrapper for WhatCounts HTTP API
Home-page: UNKNOWN
Author: Jon Baldivieso
Author-email: jonb@onenw.org
License: UNKNOWN
Platform: UNKNOWN
Classifier: Programming Language :: Python
Classifier: Topic :: Software Development :: Libraries :: Python Modules
